[
  {
    "name": "Culo",
    "description": "",
    "count": 4,
    "isActive": true,
    "isTopLevel": false,
    "lastExecution": "2024-12-12T22:52:41.381624500",
    "timeInterval": "1.3:23",
    "creationDate": "2024-12-12T22:52:41.381624500",
    "lastUpdateDate": "2025-02-25T12:50:49.028551800",
    "icon": "Man with diet",
    "sound": "No Sound"
  },
  {
    "name": "Test",
    "description": "",
    "count": 4,
    "isActive": true,
    "isTopLevel": false,
    "lastExecution": "2024-12-12T22:52:41.381624500",
    "nextExecution": "2025-02-28T02:19:32.922024300",
    "timeInterval": "1.3:23",
    "creationDate": "2024-12-12T22:52:41.381624500",
    "lastUpdateDate": "2025-02-26T22:56:32.922024300",
    "icon": "Alert",
    "sound": "Owu Woman Sound"
  },
  {
    "name": "Donatello",
    "description": "Donatello è gay",
    "count": 13,
    "isActive": true,
    "isTopLevel": false,
    "lastExecution": "2025-02-27T10:53:24.791729100",
    "nextExecution": "2025-02-27T10:54:24.791729100",
    "timeInterval": "0.0:1",
    "creationDate": "2025-01-30T15:16:53.680887600",
    "lastUpdateDate": "2025-02-25T13:24:40.680062700",
    "icon": "Man doind shopping",
    "sound": "Owu Woman Sound"
  },
  {
    "name": "Pisello",
    "description": "Ho il pisello piccolo piccolo\nMa sono contento lo stesso.... ",
    "count": 12,
    "isActive": true,
    "isTopLevel": true,
    "lastExecution": "2025-02-27T10:54:24.777058500",
    "nextExecution": "2025-02-27T10:55:24.777058500",
    "timeInterval": "0.0:1",
    "creationDate": "2025-02-26T22:44:36.391318300",
    "lastUpdateDate": "2025-02-26T22:44:36.391318300",
    "icon": "Man",
    "sound": "Owu Woman Sound"
  },
  {
    "name": "Culo_copy",
    "description": "",
    "count": 0,
    "isActive": true,
    "isTopLevel": false,
    "lastExecution": "2024-12-12T22:52:41.381624500",
    "timeInterval": "1.3:23",
    "creationDate": "2025-02-26T22:46:18.941257100",
    "lastUpdateDate": "2025-02-26T22:46:18.941257100",
    "icon": "Man with diet",
    "sound": "No Sound"
  }
]